SpotYourSpotify/__init__.py
SpotYourSpotify/play.py
SpotYourSpotify/quiz/__init__.py
SpotYourSpotify/quiz/playgame.py
SpotYourSpotify/quiz/quizbuilder.py
SpotYourSpotify/stats/__init__.py
SpotYourSpotify/stats/readdata.py
SpotYourSpotify/stats/showstats.py
SpotYourSpotify-0.0.2.dist-info/LICENSE.txt
SpotYourSpotify-0.0.2.dist-info/METADATA
SpotYourSpotify-0.0.2.dist-info/WHEEL
SpotYourSpotify-0.0.2.dist-info/top_level.txt
SpotYourSpotify-0.0.2.dist-info/RECORD
