Metadata-Version: 2.1
Name: SpotYourSpotify
Version: 0.0.2
Summary: A package that contains two subpackages: stats and quiz. Stats allows users to gain insights about their Spotify playlist such as top artist, longest song, slowest song, etc. Quiz allows users to enter a game where they will be questioned on how well they know their playlist. The program will read a CSV file of the user playlist that users can obtain using Exportify.
Author-email: "Jason Samuel Suwito, Seamus Riordan-Short" <jason.suwito@outlook.com>
Project-URL: Homepage, https://github.com/seamusprs/spotyour3
Project-URL: Issues, https://github.com/seamusprs/spotyour3/issues
Classifier: Programming Language :: Python :: 3
Classifier: License :: OSI Approved :: Apache Software License
Classifier: Operating System :: OS Independent
Requires-Python: >=3.8
License-File: LICENSE.txt
